[
    {
        "id": 0,
        "title": "파우 요치, 첫 솔로곡 오늘(22일) 발매…식케이·브라이언 체이스 지원 사격",
        "content": "첫 국내 솔로 싱글을 발표한다. 22일 오후 6시 요치는 각종 온라인 음원 플랫폼을 통해 솔로 싱글 ‘블로우 유어 마인드 (Feat. 식케이, 브라이언 체이스)’를 발매한다. 특히 이번 싱글은 세계적인 DJ 겸 프로듀서 디플로와 킹 헨리가 프로듀싱을 맡았고, 그래미...",
        "link": "http://v.daum.net/v/20260522143737889",
        "date": "2026.05.22",
        "media": "일간스포츠"
    },
    {
        "id": 1,
        "title": "파우 요치, 식케이 피처링 첫 솔로 발매... “설렌다”",
        "content": "사진=그리드엔터테인먼트 제공 그룹 파우 리더 요치가 식케이와 손잡고 국내 첫 솔로 싱글을 발표한다 요치는 오는 22일 솔로 싱글 ‘블로우 유어 마인드 (Feat. 식케이·브라이언 체이스)’를 발매한다. 파우 활동을 통해 자신만의 색깔을 구축해온 요치는 이번...",
        "link": "http://v.daum.net/v/20260514080500626",
        "date": "2026.05.14",
        "media": "일간스포츠"
    },
    {
        "id": 2,
        "title": "\"여기가 경찰서입니까\"…'마약 자수' 래퍼 식케이, 선처 요구 통할까",
        "content": "래퍼 식케이/사진=한경DB 마약 투약 사실을 자수한 후 재판에 넘겨져 1심에서 집행유예를 선고받은 래퍼 식케이(본명 권민식·32)의 2심 결과가 나온다. 서울서부지법 형사항소2-1부(부장판사 정성균)는 30일 오전 마약류 관리에 관한 법률 위반(대마) 등 혐의로...",
        "link": "http://v.daum.net/v/20260430085508583",
        "date": "2026.04.30",
        "media": "한국경제"
    },
    {
        "id": 3,
        "title": "‘마약 자수’ 래퍼 식케이, 실형 피했다… 法 “앞으로는 조심하라”",
        "content": "징역 10개월에 집행유예 2년 엑스터시와 대마 등 마약을 투약한 혐의로 재판에 넘겨져 1심에서 징역형 집행유예를 선고 받은 래퍼 식케이(본명 권민식)가 30일 오전 서울 마포구 서울서부지법에서 열린 항소심 선고공판에 출석하고 있다. 2026.4.30 뉴스1 마약 투약...",
        "link": "http://v.daum.net/v/20260430104635509",
        "date": "2026.04.30",
        "media": "서울신문"
    },
    {
        "id": 4,
        "title": "경찰 찾아가 마약 투약 자수한 래퍼 식케이, 2심에서도 실형 면했다",
        "content": "[아이뉴스24 김동현 기자] 경찰을 찾아가 마약 투약 사실을 자수한 래퍼 식케이(본명 권민식 씨)가 항소심에서도 징역형 집행유예를 선고받았다. 30일 법조계 등에 따르면 서울서부지법 형사항소2-1부(정성균 부장판사)는 마약류관리법 위반 혐의로 기소된 권 씨에게...",
        "link": "http://v.daum.net/v/20260430110834810",
        "date": "2026.04.30",
        "media": "아이뉴스24"
    },
    {
        "id": 5,
        "title": "'마약 자수' 식케이 항소심도 집유…검찰 항소 기각",
        "content": "엑스터시와 대마 등 마약을 투약한 혐의로 재판에 넘겨져 1심에서 징역형 집행유예를 선고받은 래퍼 식케이(본명 권민식)가 30일 오전 서울 마포구 서울서부지방법원에서 열린 항소심 선고공판에 출석하고 있다. 뉴스1 [파이낸셜뉴스] 마약 투약 혐의로 재판에 넘겨...",
        "link": "http://v.daum.net/v/20260430104533451",
        "date": "2026.04.30",
        "media": "파이낸셜뉴스"
    },
    {
        "id": 6,
        "title": "래퍼 식케이, 마약 투약 항소심에도 집행유예 선고 “엄벌” [왓IS]",
        "content": "가수 식케이가 12일 오후 서울 강남구 루이비통 서울 도산에서 열린 '2024 S/S 남성복 컬렉션' 공개 기념 포토월 행사에 참석해 포즈를 취하고 있다. 서병수 기자 qudtn@edaily.co.kr /2024.01.12/ 마약 투약 혐의로 기소된 래퍼 식케이(본명 권민식)가 항소심에서도...",
        "link": "http://v.daum.net/v/20260430103608924",
        "date": "2026.04.30",
        "media": "일간스포츠"
    },
    {
        "id": 7,
        "title": "'마약 자수' 식케이 오늘(30일) 항소심 선고…징역 3년6개월 구형",
        "content": "데일리 포토 [티브이데일리 김지하 기자] 마약 투약 사실을 자수한 뒤 재판에 넘겨져 1심에서 징역형 집행유예를 선고받은 래퍼 식케이(본명 권민식·32)의 항소심 선고가 오늘(30일) 내려진다. 서울서부지법 형사항소2-1부(부장판사 정성균)는 이날 오전 마약류...",
        "link": "http://v.daum.net/v/20260430075132859",
        "date": "2026.04.30",
        "media": "티브이데일리"
    },
    {
        "id": 8,
        "title": "“여기가 경찰서입니까” ‘마약 자수’ 래퍼 식케이 원심 유지 [세상&]",
        "content": "식케이[본인 인스타그램] [헤럴드경제=김도윤 기자] 엑스터시와 대마 등 마약을 투약하고 재판에 넘겨진 래퍼 식케이(본명 권민식·32)가 2심에서도 1심 판단이 그대로 유지됐다. 서울서부지법 형사항소2-1부(부장판사 정성균)는 30일 오전 10시께 마약류 관리에...",
        "link": "http://v.daum.net/v/20260430103234724",
        "date": "2026.04.30",
        "media": "헤럴드경제"
    },
    {
        "id": 9,
        "title": "'마약 자수' 식케이, 항소심서도 실형 면해…\"정말 조심해야 할 것\"",
        "content": "데일리 포토 [티브이데일리 김지하 기자] 마약 투약 사실을 자수한 뒤 재판에 넘겨져 1심에서 징역형 집행유예를 선고받은 래퍼 식케이(본명 권민식·32)의 항소심에서도 실형을 면했다. 서울서부지법 형사항소2-1부(부장판사 정성균)는 30일 오전 마약류 관리에...",
        "link": "http://v.daum.net/v/20260430113932343",
        "date": "2026.04.30",
        "media": "티브이데일리"
    }
]